zora/__init__.py
"zora/core/__init__,py"
zora/core/constants.py
zora/indexer/__init__.py
zora/indexer/base.py
zora/indexer/common.py
zora/indexer/nft.py
zora/indexer/queries.py
zora/indexer/utils.py
zora/v3/__init__.py
zora/v3/common.py
zora/v3/queries.py
zora/v3/utils.py
zora-0.2.1.dist-info/WHEEL
zora-0.2.1.dist-info/METADATA
zora-0.2.1.dist-info/RECORD
