Metadata-Version: 2.1
Name: zora
Version: 0.2.1
Summary: 
Author: franalgaba
Author-email: f.algaba@outlook.es
Requires-Python: >=3.8,<4.0
Classifier: Programming Language :: Python :: 3
Classifier: Programming Language :: Python :: 3.8
Classifier: Programming Language :: Python :: 3.9
Requires-Dist: aiohttp (>=3.8.1,<4.0.0)
Requires-Dist: asyncio (>=3.4.3,<4.0.0)
Requires-Dist: pandas (>=1.4.1,<2.0.0)
Requires-Dist: requests (>=2.27.1,<3.0.0)
